{
  "@context": "https://schema.org",
  "@type": "Article",
  "headline": "Crash Gambling Cashout Strategies: Maximize Your Profits with Proven Tactics",
  "description": "Master crash gambling cashout strategies with math-backed tactics. Learn conservative, moderate, aggressive, and hybrid approaches with examples, auto-cashout setup, and bankroll management.",
  "image": "https://crashgamegambling.com/wp-content/uploads/2026/02/crash-cashout-strategies.jpg",
  "author": {
    "@type": "Organization",
    "name": "CrashGameGambling",
    "url": "https://crashgamegambling.com"
  },
  "publisher": {
    "@type": "Organization",
    "name": "CrashGameGambling",
    "logo": {
      "@type": "ImageObject",
      "url": "https://crashgamegambling.com/logo.png"
    }
  },
  "datePublished": "2026-02-02",
  "dateModified": "2026-02-02",
  "mainEntityOfPage": {
    "@type": "WebPage",
    "@id": "https://crashgamegambling.com/crash-gambling-cashout-strategies"
  },
  "articleSection": "Gambling Strategy",
  "keywords": ["crash gambling", "cashout strategy", "auto cashout", "bankroll management", "crash game tactics"],
  "about": {
    "@type": "Thing",
    "name": "Crash Gambling"
  },
  "educationalLevel": "Beginner to Intermediate",
  "learningResourceType": "Strategy Guide"
}
