{
  "@context": "https://schema.org",
  "@type": "Article",
  "headline": "Best Crypto Wallets for Crash Gambling (2026)",
  "description": "Top crypto wallets for crash gambling. Secure deposits and withdrawals, low fees, and anonymous payments at crash casinos.",
  "image": "https://cryptocrashgambling.com/wp-content/uploads/2026/02/crypto-wallets-gambling.jpg",
  "author": {
    "@type": "Organization",
    "name": "CryptoCrashGambling",
    "url": "https://cryptocrashgambling.com"
  },
  "publisher": {
    "@type": "Organization",
    "name": "CryptoCrashGambling",
    "logo": {
      "@type": "ImageObject",
      "url": "https://cryptocrashgambling.com/wp-content/uploads/logo.png"
    }
  },
  "datePublished": "2026-02-02",
  "dateModified": "2026-02-02",
  "mainEntityOfPage": {
    "@type": "WebPage",
    "@id": "https://cryptocrashgambling.com/best-crypto-wallets-for-crash-gambling"
  },
  "articleSection": "Crypto Gambling",
  "keywords": ["crypto wallets for gambling", "best crypto wallets crash", "anonymous gambling wallets", "crash casino payments"],
  "wordCount": 2100
}
