{
  "@context": "https://schema.org",
  "@type": "Article",
  "headline": "Is Crash Gambling Legal? The Complete 2026 Country-by-Country Guide",
  "description": "Is crash gambling legal? Complete 2026 country-by-country guide to crash gambling laws. US, UK, EU, Canada, Australia, Japan + tax implications + licensed casinos.",
  "image": "https://freecrashgames.com/wp-content/uploads/2026/02/crash-gambling-legal.jpg",
  "author": {
    "@type": "Organization",
    "name": "FreeCrashGames",
    "url": "https://freecrashgames.com"
  },
  "publisher": {
    "@type": "Organization",
    "name": "FreeCrashGames",
    "logo": {
      "@type": "ImageObject",
      "url": "https://freecrashgames.com/wp-content/uploads/logo.png"
    }
  },
  "datePublished": "2026-02-03",
  "dateModified": "2026-02-03",
  "mainEntityOfPage": {
    "@type": "WebPage",
    "@id": "https://freecrashgames.com/is-crash-gambling-legal"
  },
  "articleSection": "Crash Guides",
  "keywords": ["crash gambling legal", "is crash gambling legal", "crash gambling laws", "crash gambling legality by country", "crash gambling legal usa"],
  "wordCount": 2500
}
