{"id":49407,"date":"2025-11-29T22:13:08","date_gmt":"2025-11-29T22:13:08","guid":{"rendered":"https://crashgamegambling.com/2025/11/29/crash-gambling-explained/"},"modified":"2026-02-03T07:11:40","modified_gmt":"2026-02-03T07:11:40","slug":"crash-gambling-explained","status":"publish","type":"post","link":"https://crashgamegambling.com/2025/11/29/crash-gambling-explained/","title":{"rendered":"Crash Gambling Explained: How the Game Really Works (2023)"},"content":{"rendered":"<article>\n<h1>Crash Gambling Explained: How the Game Really Works</h1>\n<section>\n<h2>Introduction: What Is Crash Gambling? (300 words)</h2>\n<p>Crash gambling is a high-volatility multiplier betting game inspired by economics and probability theory. At its core, Crash is a timing game: a multiplier begins at 1.00x and increases continuously at increasing speed. Before the game crashes (hence the name), players must &#8220;cash out&#8221; to secure their bet multiplied by the current value. Failure to cash out before the crash results in immediate loss of the entire stake. There are only two outcomes per round: partial profit (cash out before crash) or total loss (crash before cashing out.</p>\n<p>The perceived simplicity of Crash hides a complex ecosystem of RNG mechanics, edge modeling, volatility profiles, cryptographic hash calculations, and transparent on-chain fairness. The game is not just random; it's verifiably random — which leads us to one of the most critical concepts in the industry: Provably Fair Gaming.</p>\n<p>In essence, provably fair algorithms allow players to independently verify that the outcome of each round was not manipulated. This is especially important in Crash gambling, where a single 2x or 200x multiplier can shape a player's entire session.</p>\n<p>Crash gambling has evolved from niche crypto platforms to mainstream exposure on major esports and betting sites. But even as popularity increases, risk remains poorly understood. The vast majority of guides out there promote &#8220;hacks,&#8221; exploit myths, or low-value strategies that fail to confront core mathematical truths.</p>\n<p>This page — maintained by &#8216;The Analyst' at CrashGameGambling.com — offers a no-hype, data-driven breakdown of the Crash gambling format:</p>\n<ul>\n<li>Verified cryptographic mechanics,</li>\n<li>Seed generation,</li>\n<li>House edge modeling,</li>\n<li>Strategic simulations, and</li>\n<li>Fairness audits.</li>\n</ul>\n<p>Players seeking verified fundamentals can refer to the Parent Guide here: <a href=\"#\" class=\"crash-cta-button\">▶️ Verify &#038; Play</a></p>\n</section>\n<hr/>\n<section>\n<h2>The Mechanics: How the Crash Multiplier is Generated via Hash Chains &#038; Seeds (400 words)</h2>\n<p>At the heart of Crash lies a deterministic yet pseudo-random multiplier generator—built using a provably fair seed mechanism. Here's how each round is computed.</p>\n<h3>1. Key Concepts: Seeds and Nonce</h3>\n<p>To guarantee fairness, every crash round uses 3 input values:</p>\n<ul>\n<li><strong>Server Seed</strong> — Secretly chosen by the server. Revealed after a hash commitment (HMAC).</li>\n<li><strong>Client Seed</strong> — Chosen by the player or preset by the platform.</li>\n<li><strong>Nonce</strong> — A counter incremented every round, ensuring each computation is unique.</li>\n</ul>\n<p>The server publishes a hashed version of its server seed BEFORE any matches begin (e.g., <code>SHA256(server_seed)</code>), committing to its values. The full seed is only revealed post-game.</p>\n<h3>2. Combining the Inputs (Hash Construction)</h3>\n<p>Using SHA256 or another cryptographic hash function, the inputs are combined:</p>\n<pre>\ncombined_input = server_seed + \"-\" + client_seed + \"-\" + nonce\n        </pre>\n<p>This triple is hashed into a fixed-length string:</p>\n<pre>\nhash_result = SHA256(combined_input)\n        </pre>\n<p>This hash is the raw entropy that generates the crash point.</p>\n<h3>3. Calculation of Crash Multiplier</h3>\n<p>From the hash result, the first 8 characters (equivalent to 32 bits) are extracted:</p>\n<pre>\nexcerpt = hash_result[:8]\ninteger_value = int(excerpt, 16)\nnormalized = integer_value / (2^32 - 1)\n        </pre>\n<p>Then, the formula for the crash multiplier becomes:</p>\n<pre>\ncrash_point = floor(100 / (1 - normalized))\n        </pre>\n<p>But more commonly, games use:</p>\n<pre>\nif HMAC(server_seed, nonce) mod 33 == 0:\n    crash_point = 1.00x  # Instant crash\nelse:\n    crash_point = floor(100 / (random_decimal + 1))\n        </pre>\n<h3>4. Why It Matters</h3>\n<p>Unlike standard slot games or roulette, crash gambling enables full transparency. Once the server seed is revealed, players can upload or process client seeds, nonces, and hash outputs using open libraries. If any anomaly appears in the hash history, cheating becomes provable.</p>\n<p>In short: seed cryptography removes opaque house control. However, it does not eliminate the statistical house edge — only proves that edge is applied fairly.</p>\n</section>\n<hr/>\n<section>\n<h2>Mathematical Analysis: Engine Behind the Edge (300 words)</h2>\n<p>Crash gambling appears &#8220;fair&#8221; due to its transparent multiplier model, but the house edge is mathematically embedded in the risk-reward schedule of the game.</p>\n<h3>1. Distribution Function</h3>\n<p>Let <em>C</em> be the crash point. The probability that the multiplier reaches at least <em>m</em> is:</p>\n<pre>\nP(C &ge; m) = 1/m\n        </pre>\n<p>This inverse proportionality creates a steep drop-off:</p>\n<ul>\n<li>50% of rounds reach 2x</li>\n<li>20% reach 5x</li>\n<li>10% reach 10x</li>\n<li>1% reach 100x</li>\n</ul>\n<p>No upper limit is programmed; however, in practice the multiplier crashes low (1.2x–3x) in most rounds.</p>\n<h3>2. House Edge</h3>\n<p>For crash games, there is no disadvantageous payout per se — it’s the <strong>rake on winnings</strong> that determines the edge.</p>\n<p>If there were no rake, expected value (EV) would be 0. Consider a flat bet at <em>m = 2x</em>:</p>\n<pre>\nEV = 1 * (1/2) - 1 * (1 - 1/2) = 0\n        </pre>\n<p>With a 2% rake:</p>\n<pre>\nEV = 0.98 * 1 * (1/2) - 1 * (1 - 1/2) = -0.01\n        </pre>\n<p>Which yields a <strong>1% house edge</strong>.</p>\n<h3>3. Crash at 1.00x</h3>\n<p>In rare cases, the round ends instantly. Most providers use:</p>\n<pre>\nP(C = 1.00x) = 1/33 &approx; 3.03%\n        </pre>\n<p>If this 3.03% is subtracted from total possible wins, it inflates rake. Some casinos publish this rate clearly, others obfuscate it in the odds curve. The implication: even short-term grinders face unpredictable total wipes in >3% of sessions — even with conservative strategies.</p>\n</section>\n<hr/>\n<section>\n<h2>Strategic Analysis: Theory vs. Reality (800 words)</h2>\n<p>The strategic appeal of Crash is founded on manipulation of timing — when to click “Cash Out.” But any systemic advantage is undermined by the underlying EV formula. Let’s break down common approaches.</p>\n<p>        <img decoding=\"async\" src=\"https://crashgamegambling.com/wp-content/uploads/2025/11/crash-strategy-2.jpg\" alt=\"Crash Strategy Crash Gambling Explained: How the Game Really Works\" title=\"\"></p>\n<h3>Strategy 1: Martingale (Progressive Doubling)</h3>\n<p><strong>Mechanism:</strong> <br />\n        &#8211; Cash out at a fixed multiplier (e.g., 2x), <br />\n        &#8211; If you lose, double your next wager.</p>\n<table class=\"crash-data-table\">\n<thead>\n<tr>\n<th>Round</th>\n<th>Bet</th>\n<th>Outcome</th>\n<th>Net</th>\n</tr>\n</thead>\n<tbody>\n<tr>\n<td>1</td>\n<td>$1</td>\n<td>Loss</td>\n<td>-$1</td>\n</tr>\n<tr>\n<td>2</td>\n<td>$2</td>\n<td>Loss</td>\n<td>-$3</td>\n</tr>\n<tr>\n<td>3</td>\n<td>$4</td>\n<td>Win</td>\n<td>+$1</td>\n</tr>\n</tbody>\n</table>\n<p>In theory, the first win recovers all losses plus a unit.</p>\n<p><strong>Problem:</strong> Crash is not a coin flip. A sequence of 8 early crashes (e.g., <2.0x) would require a $256 bet on round 9 — impractical or blocked by wager caps.</p>\n<p><strong>EV after 1000 simulations:</strong> -3.2% net loss due to payout rake and compounding tail losses. High loss probability with negative fat tails.</p>\n<h3>Strategy 2: Anti-Martingale (Paroli)</h3>\n<p><strong>Mechanism:</strong> <br />\n        &#8211; Increase bet after wins, reset after losses.</p>\n<p><strong>Example:</strong> <br />\n        &#8211; Start $1 → Win → bet $2 → Win → bet $4 → Crash = lose $4.</p>\n<p>Much safer capital-wise. Reduces drawdown from long crash streaks. However, high multipliers are needed on win sequences to recover built-up stakes.</p>\n<p><strong>Simulation:</strong> <br />\n        &#8211; Win streaks above 3 rounds are <12%, <br />\n        &#8211; Net edge still -1.4% due to rake on all compounded wins.</p>\n<h3>Strategy 3: Flat Bet with Auto-Cashout</h3>\n<p><strong>Mechanism:</strong> <br />\n        &#8211; Fixed bet + auto cashout at specific multiplier (e.g., 1.5x).</p>\n<p>This is the most common and least risky. Yet mathematically:</p>\n<pre>\nEV = 0.98 * (t - 1) * (1/t) - (1 - 1/t)\n        </pre>\n<p>Here's an EV breakdown:</p>\n<table class=\"crash-data-table\">\n<thead>\n<tr>\n<th>Auto-Cashout at</th>\n<th>Win Rate</th>\n<th>EV (1% rake)</th>\n</tr>\n</thead>\n<tbody>\n<tr>\n<td>1.2x</td>\n<td>83.33%</td>\n<td>-1.39%</td>\n</tr>\n<tr>\n<td>1.5x</td>\n<td>66.67%</td>\n<td>-1.33%</td>\n</tr>\n<tr>\n<td>2.0x</td>\n<td>50.00%</td>\n<td>-1.00%</td>\n</tr>\n<tr>\n<td>5.0x</td>\n<td>20.00%</td>\n<td>-0.40%</td>\n</tr>\n<tr>\n<td>10.0x</td>\n<td>10.00%</td>\n<td>-0.20%</td>\n</tr>\n</tbody>\n</table>\n<p>Lower multipliers = higher win rate but also higher rake drain. House rake is largest on frequent wins.</p>\n<h3>Mixed Portfolio Auto-Cashout</h3>\n<p>Split bet between low and high targets:</p>\n<table class=\"crash-data-table\">\n<thead>\n<tr>\n<th>Bet Segment</th>\n<th>Target Multiplier</th>\n<th>Stake</th>\n<th>Expected Return</th>\n</tr>\n</thead>\n<tbody>\n<tr>\n<td>A</td>\n<td>1.3x</td>\n<td>$50</td>\n<td>98.5%</td>\n</tr>\n<tr>\n<td>B</td>\n<td>8.0x</td>\n<td>$50</td>\n<td>99.6%</td>\n</tr>\n</tbody>\n</table>\n<p>Combined expected return (pre-rake): ~99.0%. After 1–3% rake: net negative.</p>\n<h3>Takeaway:</h3>\n<p>Portfolios reduce volatility but cannot inject positive EV.</p>\n<h3>Kelly Criterion Adaptation</h3>\n<p>Kelly’s formula shows how much bankroll to risk:</p>\n<pre>\nf* = (bp - q)/b\n        </pre>\n<p>Where:</p>\n<ul>\n<li><em>b</em> = multiplier – 1,</li>\n<li><em>p</em> = 1/m (probability of hitting target),</li>\n<li><em>q</em> = 1 – <em>p</em>.</li>\n</ul>\n<p>All values skew towards 0 after applying rake. Hence:</p>\n<ul>\n<li>No <strong>optimal value</strong> exists unless EV is positive.</li>\n<li>Betting full bankroll at x100 is delusional (0.01 success rate).</li>\n<li>Conservative bankroll management is mathematically mandatory.</li>\n</ul>\n</section>\n<hr/>\n<section>\n<h2>Fairness Audit: How to Verify a Game Manually (300 words)</h2>\n<p>Verifying fairness in Crash gambling ensures you’re playing a game where the results were not tampered post-facto.</p>\n<h3>Tools Needed</h3>\n<ul>\n<li>Published server seed (from game history)</li>\n<li>Client seed (your choice or default)</li>\n<li>Round nonce (typically displayed)</li>\n<li>Cryptographic library (Python, JS, or online tools)</li>\n</ul>\n<h3>Verification Steps</h3>\n<ol>\n<li><strong>Hash Generation</strong></li>\n<pre>\nimport hashlib\ninput_str = f\"{server_seed}-{client_seed}-{nonce}\"\ngame_hash = hashlib.sha256(input_str.encode()).hexdigest()\n            </pre>\n<li><strong>Crash Multiplier Extraction</strong></li>\n<pre>\nexcerpt = game_hash[:8]\nint_value = int(excerpt, 16)\nnormalized = int_value / (2**32 - 1)\ncrash = 100 / (normalized * 100 + 1)\n            </pre>\n<li><strong>Compare to Displayed Crash</strong></li>\n<p>If your computed crash point matches the round history, fairness is verified.</p>\n</ol>\n<h3>Where to Do This</h3>\n<ul>\n<li>Use <a href=\"https://bc.game\" rel=\"nofollow noopener\" target=\"_blank\">bc.game</a> – has in-app verifier</li>\n<li>Use <a href=\"https://trustdice.win/?ref=u_crashpro\" rel=\"nofollow noopener\" target=\"_blank\">TrustDice</a> – gives detailed seed history</li>\n<li>Use third-party hashing tools (SHA256 test suites)</li>\n</ul>\n<h3>Red Flags</h3>\n<ul>\n<li>No server seed history</li>\n<li>Crash outcomes not reproducible</li>\n<li>Rakes not transparently published</li>\n</ul>\n</section>\n<hr/>\n<section>\n<h2>Where to Play It Safely: Affiliate Analysis</h2>\n<table class=\"crash-data-table\">\n<thead>\n<tr>\n<th>Casino</th>\n<th>Link</th>\n<th>USP</th>\n<th>House Edge</th>\n<th>Verification</th>\n</tr>\n</thead>\n<tbody>\n<tr>\n<td>BC.Game</td>\n<td><a href=\"https://bc.game\" class=\"crash-cta-button\" rel=\"nofollow noopener\" target=\"_blank\">▶️ Verify &#038; Play</a></td>\n<td>Custom crash scripts &#038; massive public lobbies</td>\n<td>1%</td>\n<td>Full tools</td>\n</tr>\n<tr>\n<td>TrustDice</td>\n<td><a href=\"https://trustdice.win/?ref=u_crashpro\" class=\"crash-cta-button\" rel=\"nofollow noopener\" target=\"_blank\">▶️ Verify &#038; Play</a></td>\n<td>Transparent seed audit &#038; crypto faucet bonus</td>\n<td>1%</td>\n<td>Full tools</td>\n</tr>\n<tr>\n<td>Thunderpick</td>\n<td><a href=\"https://thunderpick.com\" class=\"crash-cta-button\" rel=\"nofollow noopener\" target=\"_blank\">▶️ Verify &#038; Play</a></td>\n<td>Hybrid Crash + Esports platform</td>\n<td>3%</td>\n<td>Basic logs</td>\n</tr>\n</tbody>\n</table>\n<p>Best pick for transparency: <strong>TrustDice</strong></p>\n<p>Best for scaling up with automation: <strong>BC.Game</strong></p>\n</section>\n<hr/>\n<section>\n<h2>Extended FAQ (Technical Questions)</h2>\n<h3>1. Can the House manipulate Crash rounds?</h3>\n<p>No — if using Provably Fair mechanics. The server seed is committed in advance. Manipulation would require breaking SHA256 cryptography.</p>\n<h3>2. What happens when platform changes the server seed?</h3>\n<p>Most platforms generate a seed sequence for every 10,000 rounds. Seed rotation is disclosed and historical server seeds are published for back-auditing.</p>\n<h3>3. Can withdrawal frequency impact gameplay?</h3>\n<p>No. Crash round computation is client/server deterministic. Balance or withdrawal state does not factor into RNG.</p>\n<h3>4. Can the multiplier reach infinity?</h3>\n<p>Theoretically yes, but probability approaches zero. 1000x multipliers occur ~once every 1000 rounds. Some platforms manually cap max payout (e.g., 250x).</p>\n<h3>5. Do high multipliers mean a low crash is “due”?</h3>\n<p>No. Each round is independent — the hash seed input guarantees zero memory. Belief in streaks (Gambler's Fallacy) is statistically invalid.</p>\n</section>\n<hr/>\n<section>\n<h2>Glossary</h2>\n<ul>\n<li><strong>Hash</strong>: A 1-way cryptographic fingerprint used to verify data (SHA256, HMAC).</li>\n<li><strong>Salt</strong>: Random bytes added to seed for entropy; prevents hash predictability.</li>\n<li><strong>Crash Point</strong>: The final multiplier at which the game ends for that round.</li>\n<li><strong>Wager</strong>: The bet amount placed per Crash round.</li>\n<li><strong>RTP</strong>: Return-To-Player, theoretical % of total wagered money paid back over time.</li>\n</ul>\n</section>\n<div class=\"crash-author-box\">\n<h3>CrashGameGambling.com Research Team</h3>\n<p>This report was compiled by our Fairness Auditors. We verify hash chains and test withdrawal speeds to ensure operator transparency.</p>\n</p>\n</div>\n</article>\n<p><script type=\"application/ld+json\">\n{\n            \"mainEntityOfPage\": {\n                \"@id\": \"URL_OF_THIS_PAGE\"\n    },\n    \"headline\": \"Crash Gambling Explained: How the Game Really Works\",\n    \"image\": \"IMAGE_URL\",\n    \"author\": {\n                \"name\": \"CrashGameGambling.com Research Team\"\n    },\n    \"publisher\": {\n                \"name\": \"CrashGameGambling.com\",\n        \"logo\": {\n                        \"url\": \"LOGO_URL\"\n        }\n    },\n        \"dateModified\": \"2023-01-01\",\n    \"description\": \"A comprehensive guide explaining the mechanics, probabilities, and strategies involved in Crash gambling.\"\n}\n</script></p>\n<p><script type=\"application/ld+json\">\n{\n            \"mainEntity\": [\n        {\n                        \"name\": \"Can the House manipulate Crash rounds?\",\n            \"acceptedAnswer\": {\n                                \"text\": \"No — if using Provably Fair mechanics. The server seed is committed in advance. Manipulation would require breaking SHA256 cryptography.\"\n            }\n        },\n        {\n                        \"name\": \"What happens when platform changes the server seed?\",\n            \"acceptedAnswer\": {\n                                \"text\": \"Most platforms generate a seed sequence for every 10,000 rounds. Seed rotation is disclosed and historical server seeds are published for back-auditing.\"\n            }\n        },\n        {\n                        \"name\": \"Can withdrawal frequency impact gameplay?\",\n            \"acceptedAnswer\": {\n                                \"text\": \"No. Crash round computation is client/server deterministic. Balance or withdrawal state does not factor into RNG.\"\n            }\n        },\n        {\n                        \"name\": \"Can the multiplier reach infinity?\",\n            \"acceptedAnswer\": {\n                                \"text\": \"Theoretically yes, but probability approaches zero. 1000x multipliers occur ~once every 1000 rounds. Some platforms manually cap max payout (e.g., 250x).\"\n            }\n        },\n        {\n                        \"name\": \"Do high multipliers mean a low crash is “due”?\",\n            \"acceptedAnswer\": {\n                                \"text\": \"No. Each round is independent — the hash seed input guarantees zero memory. Belief in streaks (Gambler's Fallacy) is statistically invalid.\"\n            }\n        }\n    ]\n}\n</script></p>\n","protected":false},"excerpt":{"rendered":"<p>Crash Gambling Explained: How the Game Really Works Introduction: What Is Crash Gambling? (300 words) Crash gambling is a high-volatility multiplier betting game inspired by economics [&hellip;]</p>\n","protected":false},"author":1,"featured_media":49408,"comment_status":"open","ping_status":"open","sticky":false,"template":"","format":"standard","meta":{"rank_math_internal_links_processed":["1"],"wpil_sync_report3":["1"],"rank_math_focus_keyword":["Crash Gambling Explained: How the Game Really Works"],"_rank_math_focus_keyword":["Crash Gambling Explained: How the Game Really Works"],"rank_math_description":["Dive into the mechanics of crash gambling. We analyze game trends and strategies to help you find the best cashout points and safer sites."],"_rank_math_description":["Dive into the mechanics of crash gambling. We analyze game trends and strategies to help you find the best cashout points and safer sites."],"rank_math_title":["Crash Gambling Explained: How the Game Really Works (2023)"],"_rank_math_title":["Crash Gambling Explained: How the Game Really Works (2023)"],"rank_math_og_content_image":["a:2:{s:5:\"check\";s:32:\"2b92fe2af3617812536739ec0701ecf6\";s:6:\"images\";a:1:{i:0;i:49406;}}"],"_thumbnail_id":["49408"],"_pingme":["1"],"_encloseme":["1"]},"categories":[2],"tags":[],"class_list":["post-49407","post","type-post","status-publish","format-standard","has-post-thumbnail","hentry","category-crash-gambling-basics"],"_links":{"self":[{"href":"https://crashgamegambling.com/wp-json/wp/v2/posts/49407","targetHints":{"allow":["GET"]}}],"collection":[{"href":"https://crashgamegambling.com/wp-json/wp/v2/posts"}],"about":[{"href":"https://crashgamegambling.com/wp-json/wp/v2/types/post"}],"author":[{"embeddable":true,"href":"https://crashgamegambling.com/wp-json/wp/v2/users/1"}],"replies":[{"embeddable":true,"href":"https://crashgamegambling.com/wp-json/wp/v2/comments?post=49407"}],"version-history":[{"count":2,"href":"https://crashgamegambling.com/wp-json/wp/v2/posts/49407/revisions"}],"predecessor-version":[{"id":49656,"href":"https://crashgamegambling.com/wp-json/wp/v2/posts/49407/revisions/49656"}],"wp:featuredmedia":[{"embeddable":true,"href":"https://crashgamegambling.com/wp-json/wp/v2/media/49408"}],"wp:attachment":[{"href":"https://crashgamegambling.com/wp-json/wp/v2/media?parent=49407"}],"wp:term":[{"taxonomy":"category","embeddable":true,"href":"https://crashgamegambling.com/wp-json/wp/v2/categories?post=49407"},{"taxonomy":"post_tag","embeddable":true,"href":"https://crashgamegambling.com/wp-json/wp/v2/tags?post=49407"}],"curies":[{"name":"wp","href":"https://api.w.org/{rel}","templated":true}]}}
